{"cameraMode":{"drawMode":0,"name":"Shaded","section":"Shading Mode"},"sceneLighting":true,"audioPlay":false,"sceneViewState":{"m_AlwaysRefresh":false,"showFog":true,"showSkybox":true,"showFlares":true,"showImageEffects":true,"showParticleSystems":true,"showVisualEffectGraphs":true,"m_FxEnabled":true},"in2DMode":false,"pivot":{"x":-8.575408935546875,"y":62.29692840576172,"z":-41.01727294921875},"rotation":{"x":-0.008136000484228135,"y":0.95893794298172,"z":-0.02763286419212818,"w":-0.2821916937828064},"size":280.35076904296877,"orthographic":false}